setup.cfg
setup.py
lazybones/__init__.py
lazybones.egg-info/PKG-INFO
lazybones.egg-info/SOURCES.txt
lazybones.egg-info/dependency_links.txt
lazybones.egg-info/not-zip-safe
lazybones.egg-info/top_level.txt