Metadata-Version: 1.1
Name: lazybones
Version: 0.12
Summary: Tool for scaffolding projects in a variety of languages
Home-page: https://github.com/jacobmilligan/Lazybones.git
Author: Jacob Milligan
Author-email: UNKNOWN
License: LICENSE
Download-URL: https://github.com/jacobmilligan/Lazybones/tarball/0.1
Platform: UNKNOWN
